devops/__init__.py
devops/commands/__init__.py
devops/commands/bump_version.py
devops/commands/dist_build.py
devops/commands/publish.py
devops/commands/test.py
devops/utils/__init__.py
devops/utils/os.py
devops/utils/repo.py
devops/utils/version.py
devops/utils/tests/__init__.py
devops/utils/tests/test_os.py
devops/utils/tests/test_version.py
examples/__init__.py
examples/application.py
examples/framework_ideas/__init__.py
examples/framework_ideas/dependency_injection.py
examples/framework_ideas/domain.py
examples/framework_ideas/flow.py
examples/framework_ideas/logic_programming.py
examples/framework_ideas/use_case.py
examples/framework_ideas/integrations/__init__.py
examples/framework_ideas/integrations/common.py
examples/framework_ideas/integrations/flask.py
examples/races/__init__.py
examples/races/entities.py
examples/users/__init__.py
examples/users/entities.py
examples/users/interactors.py
examples/users/model.py
examples/users/repositories.py
examples/users/services.py
examples/users/validators.py
pca/__init__.py
pca/conftest.py
pca/exceptions.py
pca/application/__init__.py
pca/application/interactor.py
pca/application/tests/__init__.py
pca/application/tests/test_interactor.py
pca/data/__init__.py
pca/data/dao.py
pca/data/descriptors.py
pca/data/errors.py
pca/data/observable.py
pca/data/predicate.py
pca/data/validation.py
pca/data/values.py
pca/data/dao/__init__.py
pca/data/dao/abstract.py
pca/data/dao/file.py
pca/data/dao/in_memory.py
pca/data/dao/tests/__init__.py
pca/data/dao/tests/test_in_memory.py
pca/data/tests/__init__.py
pca/data/tests/test_dao.py
pca/data/tests/test_descriptors.py
pca/data/tests/test_observable.py
pca/data/tests/test_predicate.py
pca/data/tests/test_schema.py
pca/data/tests/test_validation.py
pca/domain/__init__.py
pca/domain/entity.py
pca/domain/policy.py
pca/domain/repository.py
pca/domain/value_object.py
pca/integration/__init__.py
pca/integration/errors.py
pca/integration/tinydb.py
pca/integration/tests/__init__.py
python_clean_architecture-0.0.6.dist-info/LICENSE
python_clean_architecture-0.0.6.dist-info/METADATA
python_clean_architecture-0.0.6.dist-info/WHEEL
python_clean_architecture-0.0.6.dist-info/top_level.txt
python_clean_architecture-0.0.6.dist-info/RECORD
