Metadata-Version: 2.1
Name: python-clean-architecture
Version: 0.0.6
Summary: A Python toolkit for applications driven by the Clean Architecture
Home-page: https://github.com/pcah/python-clean-architecture
Author: lhaze
Author-email: lhaze@lhaze.name
License: MIT License
Platform: any
Classifier: License :: OSI Approved :: MIT License
Classifier: Programming Language :: Python
Classifier: Programming Language :: Python :: 3 :: Only
Classifier: Programming Language :: Python :: 3.6
Classifier: Programming Language :: Python :: 3.7
Classifier: Programming Language :: Python :: 3.8
Classifier: Operating System :: OS Independent
Classifier: Topic :: Software Development
Classifier: Intended Audience :: Developers
Classifier: Development Status :: 2 - Pre-Alpha
Requires-Dist: gitpython
Requires-Dist: twine
Requires-Dist: virtualenv
Requires-Dist: wheel
Requires-Dist: dataclasses ; python_version < "3.7"
